{
  "$schema": "../../schema/hoikuryo.schema.json",
  "id": "gunma-kiryu",
  "name": "群馬県桐生市",
  "municipalityCode": "102041",
  "prefecture": "群馬県",
  "municipalityType": "その他市",
  "fiscalYear": 2026,
  "asOf": "2026-07-21",
  "nextCheckDue": "2027-04-01",
  "sources": [
    {
      "id": "fee-pdf",
      "title": "令和8年度 桐生市公立幼稚園、公立・私立保育園、認定こども園保育料",
      "publisher": "桐生市子育て支援課",
      "url": "https://www.city.kiryu.lg.jp/_res/projects/default_project/_page_/001/001/361/r8hoikuryo.pdf",
      "landingUrl": "https://www.city.kiryu.lg.jp/kosodate/1009669/hoikuen/1001361.html",
      "contentType": "pdf",
      "checkedAt": "2026-07-21",
      "tier": "municipality",
      "note": "2頁もの。1頁目に3号認定（3歳未満児）・1号認定（3歳以上児）・2号認定（3歳以上児）の月額表（Ａ・Ｂ・Ｃ・Ｄ1〜Ｄ13の16階層。ひとり親世帯等/以外の別、（）内は2人目児童の額）、2頁目に多子軽減・副食費免除・控除除外規定等の備考を収録。★結合セルが多く単純なテキスト抽出では列がずれるため、PyMuPDF の page.find_tables() で座標ベースに表構造を復元して読んだ。"
    }
  ],
  "disclaimer": "本データは桐生市の公式資料に基づく参考情報です。実際の保育料は世帯状況・税額の確定内容により決定されます。最終的な金額は必ず桐生市（子育て支援課）の決定通知および公式資料をご確認ください。",
  "scope": {
    "includes": [
      "公立・私立保育園・認定こども園の3号認定子どもの保育料のうち3歳未満児・一般世帯（ひとり親世帯等以外）・第1子分",
      "保育標準時間認定・保育短時間認定の別"
    ],
    "excludes": [
      "1号認定・2号認定（3歳以上児）の保育料（国の幼児教育・保育無償化により無償のため本ファイルのtiersには3号認定・3歳未満児分のみ収録）",
      "2号認定子ども（3歳〜5歳児）の副食費（保護者の実費負担。年収360万円未満相当世帯・第3子以降・生活保護世帯・市民税非課税世帯は免除）",
      "ひとり親世帯等（母子・父子世帯等、各種障害者手帳交付世帯等）の軽減額（一般世帯の額と別建てのため本ファイルには一般世帯分のみ収録。note参照）",
      "第2子の保育料（本ファイルのtiersは第1子の額のみ収録。note参照）"
    ]
  },
  "bracketBasis": {
    "basis": "市町村民税所得割額",
    "householdScope": "世帯の市町村民税額により決定する（各月初日の支給認定保護者の属する世帯の階層区分）。",
    "taxYearRule": "階層区分は、4月から8月分は前年度分の市町村民税の額、9月から翌年3月分は当年度分の市町村民税の額により算定する。",
    "deductionsIgnored": [
      "寄付金控除",
      "住宅借入金等特別控除",
      "配当控除",
      "外国税額控除"
    ],
    "sourceId": "fee-pdf",
    "checkedAt": "2026-07-21",
    "verify": {
      "expect": ["【寄付金控除、住宅借入金等特別控除、配当控除、外国税額控除】"]
    },
    "note": "★6/8換算について★ 桐生市は中核市・施行時特例市のいずれでもない一般市。fee-pdfに政令指定都市の6/8税率換算に関する記載は見当たらなかった（非該当・未確認）。★階層区分★ Ａ=生活保護世帯等（isWelfare）、Ｂ=市町村民税非課税世帯（isNonTaxable）、Ｃ=所得割非課税・均等割課税世帯（所得割額0円）。incomeMin/incomeMaxはＡ・Ｂを便宜上0/0、Ｃをincomeｍin 0・incomeMax 1とした上でＤ1のincomeMinを1に接続させている。★Ｄ2階層の分割統合★ 原典はＤ2階層を『48,600円以上57,700円未満』『57,700円以上58,600円未満』の2セルに分けて掲載するが、両セルの金額が11,800円/11,500円で完全一致するため単一階層（48,600円以上58,600円未満）として統合した（秋田市・千歳市と同型の統合）。★ひとり親世帯等の軽減★ 母子・父子世帯等、在宅障害児（者）のいる世帯等（fee-pdfで定義）は、Ｃ〜Ｄ5相当（所得割77,100円未満）で一般世帯より低い額になる: Ｃ=3,000/2,900円、Ｄ1=3,800/3,700円、Ｄ2=4,100/4,000円、Ｄ3=4,300/4,200円、Ｄ4=5,600/5,500円、Ｄ5=6,200/6,100円（標準時間/短時間）。所得割77,100円を超えると一般世帯と同額（Ｄ5の20,800円/20,400円で一致）になる。本ファイルのtiersには一般世帯の額のみ収録し、この軽減はこのnoteに原典表記のまま保存した。★税額不明時★ 保育料算定に必要な書類が未提出・市町村民税未申告等で課税額が確認できない場合、最高階層（Ｄ13）の保育料となる旨をfee-pdfに明記。★年度途中3歳到達★ 年度途中で満3歳に到達した場合、その年度中は3号認定の保育料を適用する旨を明記（他自治体と同様）。"
  },
  "ageClasses": [
    {
      "key": "under3",
      "label": "3歳未満児",
      "rule": "各月初日時点の年齢。年度途中で満3歳に到達しても、その年度中は3号認定の保育料を適用する。"
    },
    {
      "key": "age3plus",
      "label": "3歳以上児",
      "rule": "各月初日時点で3歳以上の子ども。"
    }
  ],
  "freeTuition": {
    "age3plusFree": {
      "value": true,
      "label": "3歳以上児（1号・2号認定）は幼児教育・保育の無償化により保育料0円",
      "sourceId": "fee-pdf",
      "checkedAt": "2026-07-21",
      "verify": {
        "expect": ["幼児教育・保育の無償化により"]
      },
      "amendmentNote": "なし(2026-07-21時点)",
      "note": "国の幼児教育・保育無償化（令和元年10月開始）による。2号認定子どもの副食費は保護者の実費負担となるが、年収360万円未満相当世帯・第3子以降・生活保護世帯・市民税非課税世帯は免除される（桐生市第3子以降副食費免除事業を含む）。"
    },
    "multiChildPolicy": {
      "countingRule": {
        "value": "1号認定は市町村民税所得割課税額77,101円未満、2・3号認定は57,700円未満（ひとり親世帯等は77,101円未満）の世帯は、扶養義務者と生計を一にする子どもが複数いる場合、年齢が高い順に1人目・2人目とカウント（年齢制限なし）。それ以外の世帯は、幼稚園・保育所・認定こども園・特別支援学校幼稚部・児童心理治療施設通所部・児童発達支援・医療型児童発達支援・地域型保育給付対象事業の入所・利用児童の範囲内で年齢が高い順にカウント。",
        "sourceId": "fee-pdf",
        "checkedAt": "2026-07-21",
        "verify": {
          "expect": ["年齢が高い順に1人目、2人目と数えます"]
        },
        "amendmentNote": "なし(2026-07-21時点)"
      },
      "secondChild": {
        "value": "1人目の額の概ね半額（fee-pdf別表の（）内の額）。",
        "sourceId": "fee-pdf",
        "checkedAt": "2026-07-21",
        "verify": {
          "expect": ["２人目・・・保育料金表の（　）内の額"]
        },
        "amendmentNote": "なし(2026-07-21時点)"
      },
      "thirdChildOnwards": {
        "value": 0,
        "unit": "JPY/month",
        "label": "3人目は無料（申請が必要な場合がある）",
        "sourceId": "fee-pdf",
        "checkedAt": "2026-07-21",
        "verify": {
          "expect": ["３人目・・・無料（申請が必要な場合があります。）"]
        },
        "amendmentNote": "なし(2026-07-21時点)",
        "note": "桐生市第3子以降保育料無料化事業（3号認定・0〜2歳児）として、桐生市在住・市民税申告済み・同一世帯で子ども3人以上扶養・保育料滞納なしの要件を満たす場合に申請により無料または副食費免除となる制度がある。"
      }
    },
    "localExtension": "桐生市独自に第3子以降の保育料無料化事業・副食費免除事業を実施（申請制）。"
  },
  "tiers": [
    {
      "tier": "Ａ",
      "label": "生活保護世帯等",
      "incomeMin": 0,
      "incomeMax": 0,
      "isWelfare": true,
      "fees": {
        "under3": { "standard": 0, "short": 0 }
      }
    },
    {
      "tier": "Ｂ",
      "label": "市町村民税非課税世帯",
      "incomeMin": 0,
      "incomeMax": 0,
      "isNonTaxable": true,
      "fees": {
        "under3": { "standard": 0, "short": 0 }
      }
    },
    {
      "tier": "Ｃ",
      "label": "所得割非課税（均等割課税）世帯",
      "incomeMin": 0,
      "incomeMax": 1,
      "fees": {
        "under3": { "standard": 7200, "short": 7000 }
      }
    },
    {
      "tier": "Ｄ1",
      "label": "所得割課税額 48,600円未満",
      "incomeMin": 1,
      "incomeMax": 48600,
      "fees": {
        "under3": { "standard": 8800, "short": 8600 }
      }
    },
    {
      "tier": "Ｄ2",
      "label": "所得割課税額 48,600円以上58,600円未満（原典は57,700円で分割されるが金額が完全一致するため統合）",
      "incomeMin": 48600,
      "incomeMax": 58600,
      "fees": {
        "under3": { "standard": 11800, "short": 11500 }
      }
    },
    {
      "tier": "Ｄ3",
      "label": "所得割課税額 58,600円以上68,000円未満",
      "incomeMin": 58600,
      "incomeMax": 68000,
      "fees": {
        "under3": { "standard": 14200, "short": 13900 }
      }
    },
    {
      "tier": "Ｄ4",
      "label": "所得割課税額 68,000円以上77,100円未満",
      "incomeMin": 68000,
      "incomeMax": 77100,
      "fees": {
        "under3": { "standard": 18800, "short": 18400 }
      }
    },
    {
      "tier": "Ｄ5",
      "label": "所得割課税額 77,100円以上97,000円未満",
      "incomeMin": 77100,
      "incomeMax": 97000,
      "fees": {
        "under3": { "standard": 20800, "short": 20400 }
      }
    },
    {
      "tier": "Ｄ6",
      "label": "所得割課税額 97,000円以上107,000円未満",
      "incomeMin": 97000,
      "incomeMax": 107000,
      "fees": {
        "under3": { "standard": 26800, "short": 26300 }
      }
    },
    {
      "tier": "Ｄ7",
      "label": "所得割課税額 107,000円以上117,000円未満",
      "incomeMin": 107000,
      "incomeMax": 117000,
      "fees": {
        "under3": { "standard": 31000, "short": 30400 }
      }
    },
    {
      "tier": "Ｄ8",
      "label": "所得割課税額 117,000円以上127,000円未満",
      "incomeMin": 117000,
      "incomeMax": 127000,
      "fees": {
        "under3": { "standard": 34400, "short": 33800 }
      }
    },
    {
      "tier": "Ｄ9",
      "label": "所得割課税額 127,000円以上169,000円未満",
      "incomeMin": 127000,
      "incomeMax": 169000,
      "fees": {
        "under3": { "standard": 36900, "short": 36200 }
      }
    },
    {
      "tier": "Ｄ10",
      "label": "所得割課税額 169,000円以上211,200円未満",
      "incomeMin": 169000,
      "incomeMax": 211200,
      "fees": {
        "under3": { "standard": 39000, "short": 38300 }
      }
    },
    {
      "tier": "Ｄ11",
      "label": "所得割課税額 211,200円以上301,000円未満",
      "incomeMin": 211200,
      "incomeMax": 301000,
      "fees": {
        "under3": { "standard": 40600, "short": 39900 }
      }
    },
    {
      "tier": "Ｄ12",
      "label": "所得割課税額 301,000円以上397,000円未満",
      "incomeMin": 301000,
      "incomeMax": 397000,
      "fees": {
        "under3": { "standard": 43000, "short": 42200 }
      }
    },
    {
      "tier": "Ｄ13",
      "label": "所得割課税額 397,000円以上",
      "incomeMin": 397000,
      "incomeMax": null,
      "fees": {
        "under3": { "standard": 44000, "short": 43200 }
      }
    }
  ],
  "verify": {
    "sourceId": "fee-pdf",
    "expect": [
      "令和８年度　保育料の御案内",
      "44,000",
      "397,000円以上"
    ]
  }
}
