{
  "$comment": "適正体重・BMIの基準（記事Q4-041）のデータ表。data/seido/ ではなく data/tables/ に置いているのは、BMIの判定基準が『日本肥満学会が定める学会基準』であり、法令・公的制度・厚労省が策定する基準ではないため（厚労省 e-ヘルスネットは学会基準を紹介する立場）。ただし『目標とするBMIの範囲』のみは厚労省が健康増進法第16条の2に基づき策定する『日本人の食事摂取基準（2025年版）』の値であり、制度性がある。出典は .go.jp ドメインの公的サイトに限定し、日本肥満学会サイト（jasso.or.jp）は許可ドメイン外のため参照していない。取得できなかった値は null＋未確認とし、推定値は入れていない。",
  "lastVerified": "2026-07-17",
  "nextCheckDue": "2027-04-01",
  "sources": [
    {
      "id": "ehealthnet-bmi",
      "label": "BMI | 生活習慣病などの情報(e-ヘルスネット) | 健康日本21アクション支援システム（厚生労働省）",
      "url": "https://kennet.mhlw.go.jp/information/information/dictionary/metabolic/ym-002.html",
      "publisher": "厚生労働省",
      "contentType": "html",
      "checkedAt": "2026-07-17",
      "lastUpdatedOnSource": "2024-02-15",
      "note": "BMIの計算式・低体重18.5未満・肥満25以上（日本肥満学会基準）の根拠。★旧URL www.e-healthnet.mhlw.go.jp は2026-07-17時点で名前解決できない（DNS NXDOMAIN）。e-ヘルスネットは『健康日本21アクション支援システム』（kennet.mhlw.go.jp）に統合されている。旧URLを出典に書かないこと。★"
    },
    {
      "id": "ehealthnet-himan",
      "label": "肥満と肥満症 | 生活習慣病などの情報(e-ヘルスネット)（厚生労働省）",
      "url": "https://kennet.mhlw.go.jp/information/information/metabolic/m-05-009.html",
      "publisher": "厚生労働省",
      "contentType": "html",
      "checkedAt": "2026-07-17",
      "lastUpdatedOnSource": "2024-10-24",
      "note": "肥満（BMI25以上）と肥満症の区別、肥満症の診断に必要な11の健康障害、BMIと総死亡のU字型関連の根拠。"
    },
    {
      "id": "mhlw-dri2025-points",
      "label": "日本人の食事摂取基準（2025年版）の策定ポイント（スライド集）（厚生労働省）",
      "url": "https://www.mhlw.go.jp/content/10904750/001396865.pdf",
      "landingUrl": "https://www.mhlw.go.jp/stf/newpage_49171.html",
      "publisher": "厚生労働省",
      "contentType": "pdf",
      "checkedAt": "2026-07-17",
      "note": "目標とするBMIの範囲（18歳以上・年齢別）の根拠。表1「目標とするBMIの範囲（18歳以上）」を掲載。★報告書本体の分割版PDFはテキスト抽出時に文字化けするため、同一の表を掲載する本スライド集を用いた。★"
    },
    {
      "id": "cfa-shokuseikatsu-shishin",
      "label": "妊娠前からはじめる妊産婦のための食生活指針 解説要領（令和3年3月）（こども家庭庁／策定時：厚生労働省）",
      "url": "https://www.cfa.go.jp/assets/contents/node/basic_page/field_ref_resources/a29a9bee-4d29-482d-a63b-5f9cb8ea0aa2/aaaf2a82/20230401_policies_boshihoken_shokuji_02.pdf",
      "landingUrl": "https://www.cfa.go.jp/policies/boshihoken/shokuji",
      "publisher": "こども家庭庁",
      "contentType": "pdf",
      "checkedAt": "2026-07-17",
      "note": "妊娠中の体重増加指導の目安（表8）の根拠。2021年（令和3年）3月改定版。表8の脚注に「日本肥満学会の肥満度分類に準じた」と明記されており、肥満1度・肥満2度以上のBMI境界も本資料から確認できる。"
    }
  ],
  "bmiFormula": {
    "expression": "BMI = 体重(kg) ÷ 身長(m)の2乗",
    "sourceId": "ehealthnet-bmi",
    "sourceQuote": "体格を表す指標として国際的に用いられている指数で、［体重（kg）］÷［身長（m）の2乗］で求められます（身長はcmではなくmで計算します）。",
    "note": "身長はcmではなくmで計算する。実装時の単位ミスが最も多いポイント。",
    "unit": "kg/m2"
  },
  "obesityClassification": {
    "$comment": "肥満度分類。★出典の制約★ 完全な分類表（肥満1度〜4度）は日本肥満学会『肥満症診療ガイドライン2022』に掲載されているが、日本肥満学会のサイト（www.jasso.or.jp）は本プロジェクトの許可ドメイン外のため参照していない。.go.jp ドメインで確認できたのは以下の範囲のみ。確認できなかった境界値は null＋未確認としている。",
    "standardSetter": "日本肥満学会（厚生労働省 e-ヘルスネットが紹介）",
    "categories": [
      {
        "code": "UNDERWEIGHT",
        "label": "低体重（やせ）",
        "bmiFrom": null,
        "bmiTo": 18.5,
        "rangeLabel": "18.5未満",
        "confirmed": true,
        "sourceId": "ehealthnet-bmi",
        "sourceQuote": "また、18.5未満は「低体重」（やせ）に分類されます。",
        "note": "bmiFrom が null なのは下限が定められていないため（未確認ではない）。"
      },
      {
        "code": "NORMAL",
        "label": "普通体重",
        "bmiFrom": 18.5,
        "bmiTo": 25.0,
        "rangeLabel": "18.5以上25.0未満",
        "confirmed": true,
        "sourceId": "cfa-shokuseikatsu-shishin",
        "sourceQuote": "普通体重 18.5 以上 25.0 未満",
        "note": "こども家庭庁「妊産婦のための食生活指針 解説要領」表8（脚注2で「日本肥満学会の肥満度分類に準じた」と明記）で、普通体重の範囲が18.5以上25.0未満であることを確認。e-ヘルスネットも「18.5未満＝低体重」「25以上＝肥満」と記述しており整合する。"
      },
      {
        "code": "OBESE_1",
        "label": "肥満（1度）",
        "bmiFrom": 25.0,
        "bmiTo": 30.0,
        "rangeLabel": "25.0以上30.0未満",
        "confirmed": true,
        "sourceId": "cfa-shokuseikatsu-shishin",
        "sourceQuote": "肥満（１度） 25.0 以上 30.0 未満",
        "note": "同上・表8。"
      },
      {
        "code": "OBESE_2",
        "label": "肥満（2度）",
        "bmiFrom": 30.0,
        "bmiTo": null,
        "rangeLabel": null,
        "confirmed": false,
        "sourceId": "cfa-shokuseikatsu-shishin",
        "sourceQuote": "肥満（２度以上） 30.0 以上",
        "note": "未確認: 下限30.0は こども家庭庁「妊産婦のための食生活指針 解説要領」表8（「肥満（２度以上） 30.0 以上」）で確認できたが、上限（肥満2度と3度の境界＝35.0とされる）を .go.jp ドメインの一次情報で確認できなかったため bmiTo は null。探索経緯 — (1) e-ヘルスネットのBMIページ・肥満と肥満症ページ（kennet.mhlw.go.jp）はいずれも25以上を肥満とするのみで度数分類表を掲載していない、(2) site:go.jp で「肥満3度」「肥満度分類」を検索したところ完全な分類表は www.jasso.or.jp（日本肥満学会）のPDFにしか存在しなかった。要追加ドメイン: www.jasso.or.jp（日本肥満学会＝肥満度分類の策定主体）。"
      },
      {
        "code": "OBESE_3",
        "label": "肥満（3度）",
        "bmiFrom": null,
        "bmiTo": null,
        "rangeLabel": null,
        "confirmed": false,
        "sourceId": null,
        "sourceQuote": null,
        "note": "未確認: 肥満3度のBMI範囲（35.0以上40.0未満とされる）を .go.jp ドメインの一次情報で確認できなかった。探索経緯は OBESE_2 と同じ。要追加ドメイン: www.jasso.or.jp。記事では肥満2度以上の細分は書かず、「BMI30以上は肥満（2度以上）。詳細な分類は日本肥満学会の肥満度分類による」と留めること。"
      },
      {
        "code": "OBESE_4",
        "label": "肥満（4度）",
        "bmiFrom": null,
        "bmiTo": null,
        "rangeLabel": null,
        "confirmed": false,
        "sourceId": null,
        "sourceQuote": null,
        "note": "未確認: 肥満4度のBMI範囲（40.0以上とされる）を .go.jp ドメインの一次情報で確認できなかった。探索経緯は OBESE_2 と同じ。要追加ドメイン: www.jasso.or.jp。"
      }
    ],
    "obesityThreshold": {
      "value": 25.0,
      "unit": "kg/m2",
      "sourceId": "ehealthnet-bmi",
      "sourceQuote": "日本人は欧米人よりもBMIが平均的に低いことが特徴であり、日本肥満学会の基準では25以上を肥満と定義しています。",
      "note": "日本の基準。WHOの基準では30以上をObese（肥満）としており、日本と国際基準は異なる。"
    },
    "whoObesityThreshold": {
      "value": 30.0,
      "unit": "kg/m2",
      "sourceId": "ehealthnet-bmi",
      "sourceQuote": "計算方法は世界共通ですが、肥満の判定基準は国によって異なり、WHO（世界保健機構）の基準では30以上を\"Obese\"（肥満）としています。",
      "note": "★記事執筆時の注意★ 海外の記事・研究の「肥満」と日本の「肥満」はBMIの基準が違う。"
    }
  },
  "obesityVsObesityDisease": {
    "$comment": "『肥満』と『肥満症』は別物。ここを混同した記事はYMYL上の重大な誤り。",
    "obesityDefinition": {
      "text": "脂肪組織に脂肪が過剰に蓄積した状態で、体格指数（BMI＝体重[kg]/身長[m]2）が25kg/m2以上のもの",
      "sourceId": "ehealthnet-himan",
      "sourceQuote": "肥満とは、脂肪組織に脂肪が過剰に蓄積した状態で、体格指数（BMI＝体重[kg]/身長[m]2）が25kg/m2以上のものをいいます。"
    },
    "obesityDiseaseDefinition": {
      "text": "肥満に起因・関連する健康障害を合併するか、その合併が予測され、減量を必要とする疾患",
      "sourceId": "ehealthnet-himan",
      "sourceQuote": "それに対して、肥満症とは、肥満に起因・関連する健康障害を合併するか、その合併が予測され、減量を必要とする疾患をいいます。"
    },
    "obesityIsNotTreatmentTarget": {
      "text": "肥満だけでは治療の対象とはならない（治療が必要な「肥満症」とは区別される）",
      "sourceId": "ehealthnet-himan",
      "sourceQuote": "肥満だけでは治療の対象とはなりません。"
    },
    "visceralFatObesity": {
      "text": "内臓脂肪型肥満症の場合は、将来、健康障害の合併が予測されることから、健康障害がなくても肥満症と診断される",
      "sourceId": "ehealthnet-himan",
      "sourceQuote": "また 内臓脂肪型肥満症 の場合は、将来、健康障害の合併が予測されることから、下記の健康障害がなくても肥満症と診断されます。"
    },
    "healthDisordersForDiagnosis": {
      "list": [
        "耐糖能障害（2型糖尿病・耐糖能異常など）",
        "脂質異常症",
        "高血圧",
        "高尿酸血症・痛風",
        "冠動脈疾患",
        "脳梗塞・一過性脳虚血発作",
        "非アルコール性脂肪性肝疾患",
        "月経異常・女性不妊",
        "閉塞性睡眠時無呼吸症候群・肥満低換気症候群",
        "運動器疾患（変形性関節症：膝関節・股関節・手指関節、変形性脊椎症）",
        "肥満関連腎臓病"
      ],
      "count": 11,
      "sourceId": "ehealthnet-himan",
      "sourceQuote": "[1] 肥満に起因ないし関連する健康障害〈肥満症の診断に必要な健康障害〉",
      "note": "この11項目のいずれかを合併し、かつBMIが25以上の場合が肥満症。"
    }
  },
  "targetBmiRange": {
    "$comment": "厚生労働省「日本人の食事摂取基準（2025年版）」表1『目標とするBMIの範囲（18歳以上）』。★肥満度分類（日本肥満学会）とは別物であり、目的も異なる（こちらはエネルギー収支バランスの維持を評価する指標）。★ 2025年版は令和7年度から使用されている現行版。",
    "editionLabel": "日本人の食事摂取基準（2025年版）",
    "sourceId": "mhlw-dri2025-points",
    "sourceQuote": "表１ 目標とするBMIの範囲（18歳以上）1,2",
    "ranges": [
      {
        "ageFrom": 18,
        "ageTo": 49,
        "ageLabel": "18〜49歳",
        "bmiFrom": 18.5,
        "bmiTo": 24.9,
        "rangeLabel": "18.5〜24.9",
        "sourceQuote": "18～49 18.5～24.9"
      },
      {
        "ageFrom": 50,
        "ageTo": 64,
        "ageLabel": "50〜64歳",
        "bmiFrom": 20.0,
        "bmiTo": 24.9,
        "rangeLabel": "20.0〜24.9",
        "sourceQuote": "50～64 20.0～24.9"
      },
      {
        "ageFrom": 65,
        "ageTo": 74,
        "ageLabel": "65〜74歳",
        "bmiFrom": 21.5,
        "bmiTo": 24.9,
        "rangeLabel": "21.5〜24.9",
        "sourceQuote": "65～74 3 21.5～24.9",
        "note": "脚注3: 総死亡率をできるだけ低く抑えるためには下限は20.0から21.0付近となるが、その他の考慮すべき健康障害等を勘案して21.5とした。"
      },
      {
        "ageFrom": 75,
        "ageTo": null,
        "ageLabel": "75歳以上",
        "bmiFrom": 21.5,
        "bmiTo": 24.9,
        "rangeLabel": "21.5〜24.9",
        "sourceQuote": "75以上3 21.5～24.9",
        "note": "脚注3は65〜74歳と同じ。"
      }
    ],
    "footnotes": [
      "1 男女共通。あくまでも参考として使用すべきである。",
      "2 上限は総死亡率の低減に加え、主な生活習慣病の有病率、医療費、高齢者及び労働者の身体機能低下との関連を考慮して定めた。",
      "3 総死亡率をできるだけ低く抑えるためには下限は20.0から21.0付近となるが、その他の考慮すべき健康障害等を勘案して21.5とした。"
    ],
    "under18": {
      "value": null,
      "note": "未確認: 18歳未満の目標とするBMIは食事摂取基準の表1（18歳以上）の対象外。小児の体格評価にはBMIではなく成長曲線・肥満度（標準体重比）が用いられるのが一般的だが、その基準値は本表の範囲外であり、.go.jp の一次情報で確認していないため null とする。18歳未満についてはこの表を適用しないこと。"
    },
    "purposeNote": "食事摂取基準の目標BMIは「エネルギーの摂取量及び消費量のバランス（エネルギー収支バランス）の維持を示す指標」として設定されたもので、肥満・やせの『判定』基準ではない。成人における観察疫学研究で総死亡率が最も低かったBMIの範囲、日本人のBMIの実態などを総合的に検証して提示されている。",
    "frailtyNote": "2025年版では、肥満ややせの予防に関して総死亡率に加えてフレイル・身体機能障害をアウトカムとした目標BMI設定であることが記述され、フレイルに関してはやせだけでなく肥満もリスク因子となることにも言及されている。"
  },
  "bmiAndMortality": {
    "$comment": "BMIと死亡率の関係。「BMI22が理想」という俗説に対する公的情報の記述。",
    "uShapedRelation": {
      "text": "日本人の観察研究では、BMIと総死亡との関連はU字型であり、太りすぎ（30kg/m2以上）でも、やせすぎ（19kg/m2未満）でも死亡率の上昇と関連し、BMIが25kg/m2前後（21〜27kg/m2）の人が死亡リスクが低いことが知られている",
      "sourceId": "ehealthnet-himan",
      "sourceQuote": "日本人の観察研究では、BMIと総死亡との関連はU字型であり、太りすぎ（30kg/m2以上）でも、やせすぎ（19kg/m2未満）でも死亡率の上昇と関連し、BMIが25kg/m2前後（21～27kg/m2）の人が死亡リスクが低いことが知られています"
    },
    "riskConcentratedAt30": {
      "text": "健康リスク増加の多くは、BMIが30kg/m2以上の人で強くみられている",
      "sourceId": "ehealthnet-himan",
      "sourceQuote": "しかし、これらの健康リスク増加の多くは、BMIが30kg/m2以上の人で強くみられています。"
    },
    "longTermCaution": {
      "text": "BMIが25〜27kg/m2を超える状態が長く続くと、高血圧や糖尿病、脂質異常症などになりやすくなる。体重に気をつけるとともに、毎年特定健診を受診して健康状態を確認することが重要",
      "sourceId": "ehealthnet-himan",
      "sourceQuote": "しかしながら、BMIが25～27kg/m2を超える状態が長く続くと、高血圧や糖尿病、脂質異常症などになりやすくなります"
    },
    "idealBmi22": {
      "value": null,
      "note": "未確認: 「BMI22が標準体重／最も病気になりにくい」という広く流布した記述の根拠を .go.jp ドメインの一次情報で確認できなかった。探索経緯 — e-ヘルスネットのBMIページ・肥満と肥満症ページ、食事摂取基準2025年版のスライド集を確認したが、「22」を標準・理想とする記述は存在しない。むしろ e-ヘルスネットは「BMIが25kg/m2前後（21〜27kg/m2）の人が死亡リスクが低い」とし、食事摂取基準は年齢別に18.5〜24.9／20.0〜24.9／21.5〜24.9の『範囲』を示している。単一の理想値としてBMI22を記事に書いてはならない。"
    }
  },
  "metabolicSyndromeNote": {
    "text": "メタボリックシンドロームの診断基準では、BMIではなく腹囲が用いられる。ただしメタボリックシンドローム予備群を拾い上げる観点から、特定健診・特定保健指導の基準には腹囲に加えてBMIも用いられる",
    "sourceId": "ehealthnet-bmi",
    "sourceQuote": "なお、メタボリックシンドロームの診断基準では、BMIではなく腹囲が用いられますが、メタボリックシンドローム予備群を拾い上げる観点から、特定健診・特定保健指導の基準には腹囲に加えてBMIも用いられます。"
  },
  "pregnancyWeightGain": {
    "$comment": "妊娠中の体重増加指導の目安。2021年（令和3年）3月の「妊娠前からはじめる妊産婦のための食生活指針」改定で示された表8。出典はこども家庭庁（策定時は厚生労働省）の解説要領PDFで、日本産科婦人科学会が提示する目安を掲載したもの。★おなかにいる赤ちゃんが一人の場合の数値。★",
    "tableLabel": "表８ 妊娠中の体重増加指導の目安",
    "sourceId": "cfa-shokuseikatsu-shishin",
    "revisedOn": "2021-03",
    "bmiBasis": "妊娠前の体重(kg) ÷ 身長(m)の2乗",
    "sourceQuote": "表８ 妊娠中の体重増加指導の目安＊1 妊娠前の体格*2 体重増加量指導の目安",
    "categories": [
      {
        "code": "UNDERWEIGHT",
        "label": "低体重（やせ）",
        "bmiFrom": null,
        "bmiTo": 18.5,
        "bmiRangeLabel": "18.5未満",
        "gainFromKg": 12,
        "gainToKg": 15,
        "gainLabel": "12〜15kg",
        "sourceQuote": "低体重（やせ） 18.5 未満 12～15 ㎏"
      },
      {
        "code": "NORMAL",
        "label": "普通体重",
        "bmiFrom": 18.5,
        "bmiTo": 25.0,
        "bmiRangeLabel": "18.5以上25.0未満",
        "gainFromKg": 10,
        "gainToKg": 13,
        "gainLabel": "10〜13kg",
        "sourceQuote": "普通体重 18.5 以上 25.0 未満 10～13 ㎏",
        "note": "★重要★ 妊娠前の体格がふつう体型に区分される方でも、BMIが低体重に近い場合は、体重増加指導の目安の上限値を参考にする（＝13kg側を目安にする）。"
      },
      {
        "code": "OBESE_1",
        "label": "肥満（1度）",
        "bmiFrom": 25.0,
        "bmiTo": 30.0,
        "bmiRangeLabel": "25.0以上30.0未満",
        "gainFromKg": 7,
        "gainToKg": 10,
        "gainLabel": "7〜10kg",
        "sourceQuote": "肥満（１度） 25.0 以上 30.0 未満  7～10 ㎏"
      },
      {
        "code": "OBESE_2_PLUS",
        "label": "肥満（2度以上）",
        "bmiFrom": 30.0,
        "bmiTo": null,
        "bmiRangeLabel": "30.0以上",
        "gainFromKg": null,
        "gainToKg": 5,
        "gainLabel": "個別対応（上限5kgまでが目安）",
        "sourceQuote": "肥満（２度以上） 30.0 以上 個別対応 （上限5 ㎏までが目安）",
        "note": "★実装上の注意★ 数値レンジではなく「個別対応」。ツールで自動計算した目安を出してはならず、必ず主治医に相談するよう誘導すること。gainFromKg が null なのは下限が示されていないため。"
      }
    ],
    "footnotes": [
      "＊１「増加量を厳格に指導する根拠は必ずしも十分ではないと認識し，個人差を考慮したゆるやかな指導を心がける．」産婦人科診療ガイドライン産科編2020 CQ 010 より",
      "＊２日本肥満学会の肥満度分類に準じた。"
    ],
    "applicability": {
      "singleton": true,
      "multipleGestation": null,
      "note": "この表はおなかにいる赤ちゃんが一人の場合の数値。多胎の場合は「それぞれの体格区分の体重増加よりも多く増加することがみられます」とされるのみで、具体的な目安値は示されていない（multipleGestation = null＝未確認）。多胎の目安を記事に書いてはならない。"
    },
    "cautionQuote": "これは、おなかにいる赤ちゃんが一人の場合の数値で、医師が妊婦の妊娠中の体重増加の指導を行うときの目安となるものであり、妊娠中の体重増加量については個人差を考慮した指導が必要になります。",
    "rationaleQuote": "妊娠中の体重増加が不足すると、早産のリスクや赤ちゃんが在胎週数に対して小さく産まれるリスクが高まります。逆に、妊娠中の体重増加が過剰だと巨大児（出生体重が4,000g を超える場合）のリスクや赤ちゃんが在胎週数に対して大きく産まれるリスクが高まります。",
    "macrosomiaThresholdG": 4000
  },
  "disclaimer": "BMIは体格を表す指標のひとつであり、筋肉量・体脂肪の分布・年齢によって同じBMIでも健康リスクは大きく異なります（e-ヘルスネットも「同じBMIでもどこに脂肪がついているかで健康への危険性は大きく異なる」としています）。BMIが基準の範囲から外れていることは、直ちに病気であることを意味しません。肥満（BMI25以上）だけでは治療の対象とはならず、治療が必要な「肥満症」とは区別されます。減量が必要かどうか、どの程度が適切かは、必ず医師にご相談ください。妊娠中の体重増加の目安は医師が指導を行うときの目安であり、個人差を考慮した指導が必要です。ご自身で目標体重を決めて食事量を減らすことは、母体と赤ちゃんの双方にリスクがあります。必ずかかりつけの産婦人科医の指示に従ってください。",
  "openIssues": [
    {
      "item": "肥満度分類の肥満2度の上限・肥満3度・肥満4度のBMI境界",
      "status": "未確認",
      "reason": "完全な肥満度分類表は日本肥満学会（www.jasso.or.jp）の『肥満症診療ガイドライン2022』にしか存在せず、当該ドメインは本プロジェクトの許可ドメイン外。厚労省 e-ヘルスネットは25以上を肥満とするのみで度数分類を掲載していない。",
      "requestedDomain": "www.jasso.or.jp"
    },
    {
      "item": "「BMI22が標準体重／理想」の根拠",
      "status": "未確認",
      "reason": ".go.jp の一次情報にBMI22を標準・理想とする記述が存在しない。俗説の可能性が高く、記事に書いてはならない。"
    },
    {
      "item": "18歳未満の目標BMI",
      "status": "対象外",
      "reason": "食事摂取基準の目標BMIの表は18歳以上が対象。小児は成長曲線・肥満度で評価する。"
    },
    {
      "item": "多胎妊娠の体重増加の目安",
      "status": "未確認",
      "reason": "食生活指針の解説要領には「それぞれの体格区分の体重増加よりも多く増加することがみられます」との記述のみで、具体値が示されていない。"
    }
  ]
}
